openamundsen/__init__.py
openamundsen/_version.py
openamundsen/cli.py
openamundsen/conf.py
openamundsen/constants.py
openamundsen/forcing.py
openamundsen/heatconduction.py
openamundsen/interpolation.py
openamundsen/landcover.py
openamundsen/liveview.py
openamundsen/model.py
openamundsen/snowmodel.py
openamundsen/statevars.py
openamundsen/surface.py
openamundsen/terrain.py
openamundsen/tridiag.py
openamundsen/util.py
openamundsen/data/configschema.yml
openamundsen/data/land_cover_class_params.yml
openamundsen/data/land_cover_class_schema.yml
openamundsen/errors/__init__.py
openamundsen/fileio/__init__.py
openamundsen/fileio/griddedoutput.py
openamundsen/fileio/meteo.py
openamundsen/fileio/pointoutput.py
openamundsen/fileio/raster.py
openamundsen/meteo/__init__.py
openamundsen/meteo/atmosphere.py
openamundsen/meteo/interpolation.py
openamundsen/meteo/precipcorr.py
openamundsen/modules/__init__.py
openamundsen/modules/canopy/__init__.py
openamundsen/modules/canopy/canopy.py
openamundsen/modules/evapotranspiration/__init__.py
openamundsen/modules/evapotranspiration/evapotranspiration.py
openamundsen/modules/evapotranspiration/soiltexture.py
openamundsen/modules/glacier/__init__.py
openamundsen/modules/glacier/glaciermodel.py
openamundsen/modules/radiation/__init__.py
openamundsen/modules/radiation/clearsky.py
openamundsen/modules/radiation/irradiance.py
openamundsen/modules/radiation/shadows.py
openamundsen/modules/radiation/sunparams.py
openamundsen/modules/snow/__init__.py
openamundsen/modules/snow/cryolayermodel.py
openamundsen/modules/snow/multilayermodel.py
openamundsen/modules/snow/snow.py
openamundsen/modules/soil/__init__.py
openamundsen/modules/soil/init.py
openamundsen/modules/soil/soil.py
openamundsen-1.1.4.dist-info/licenses/LICENSE
openamundsen-1.1.4.dist-info/METADATA
openamundsen-1.1.4.dist-info/WHEEL
openamundsen-1.1.4.dist-info/entry_points.txt
openamundsen-1.1.4.dist-info/top_level.txt
openamundsen-1.1.4.dist-info/RECORD
