Metadata-Version: 2.4
Name: openamundsen
Version: 1.1.4
Summary: Modular snow and hydroclimatological modeling framework
Author-email: openAMUNDSEN Developers <florian.hanzer@gmail.com>
License: MIT License
Project-URL: Homepage, https://github.com/openamundsen/openamundsen
Project-URL: Documentation, https://doc.openamundsen.org
Classifier: Development Status :: 5 - Production/Stable
Classifier: License :: OSI Approved :: MIT License
Classifier: Intended Audience :: Science/Research
Classifier: Programming Language :: Python :: 3
Classifier: Programming Language :: Python :: 3.8
Classifier: Programming Language :: Python :: 3.9
Classifier: Programming Language :: Python :: 3.10
Classifier: Programming Language :: Python :: 3.11
Classifier: Programming Language :: Python :: 3.12
Classifier: Programming Language :: Python :: 3.13
Requires-Python: >=3.8
License-File: LICENSE
Requires-Dist: cerberus
Requires-Dist: loguru
Requires-Dist: munch
Requires-Dist: netCDF4
Requires-Dist: numba>=0.50.1
Requires-Dist: numpy
Requires-Dist: pandas>=1.1.0
Requires-Dist: pwlf
Requires-Dist: pyproj
Requires-Dist: setuptools_scm
Requires-Dist: setuptools>=61
Requires-Dist: scipy
Requires-Dist: ruamel.yaml>=0.15.0
Requires-Dist: rasterio>=1.1.0
Requires-Dist: xarray>=0.14.0
Provides-Extra: liveview
Requires-Dist: matplotlib>=3.0.0; extra == "liveview"
Requires-Dist: PyQt6; extra == "liveview"
Provides-Extra: test
Requires-Dist: dask; extra == "test"
Requires-Dist: pooch; extra == "test"
Requires-Dist: pytest; extra == "test"
Requires-Dist: pvlib; extra == "test"
Dynamic: license-file
